tacotron2/LICENSE
tacotron2/README.md
tacotron2/audio_processing.py
tacotron2/data_utils.py
tacotron2/distributed.py
tacotron2/hparams.py
tacotron2/layers.py
tacotron2/logger.py
tacotron2/loss_function.py
tacotron2/loss_scaler.py
tacotron2/model.py
tacotron2/multiproc.py
tacotron2/plotting_utils.py
tacotron2/stft.py
tacotron2/tensorboard.png
tacotron2/text/LICENSE
tacotron2/text/__init__.py
tacotron2/text/cleaners.py
tacotron2/text/cmudict.py
tacotron2/text/numbers.py
tacotron2/text/symbols.py
tacotron2/train.py
tacotron2/utils.py
tacotron2-22.12.28.dist-info/entry_points.txt
tacotron2-22.12.28.dist-info/METADATA
tacotron2-22.12.28.dist-info/WHEEL
tacotron2-22.12.28.dist-info/RECORD
