Metadata-Version: 2.1
Name: tacotron2
Version: 22.12.28
Summary: Tacotron2 library
Home-page: http://github.com/8tm/tacotron2
Author: Tadeusz Miszczyk
Author-email: 42252259+8tm@users.noreply.github.com
Requires-Python: >=3.8,<4.0
Classifier: Environment :: Console
Classifier: Intended Audience :: Developers
Classifier: Operating System :: Unix
Classifier: Programming Language :: Python :: 3
Classifier: Programming Language :: Python :: 3.8
Classifier: Programming Language :: Python :: 3.9
Classifier: Programming Language :: Python :: 3.10
Classifier: Programming Language :: Python :: 3.11
Classifier: Programming Language :: Python :: 3 :: Only
Classifier: Programming Language :: Python :: 3.10
Classifier: Programming Language :: Python :: 3.11
Classifier: Programming Language :: Python :: 3.8
Classifier: Programming Language :: Python :: 3.9
Requires-Dist: Pillow (>=9.3.0,<10.0.0)
Requires-Dist: Unidecode (>=1.3.6,<2.0.0)
Requires-Dist: inflect (>=6.0.2,<7.0.0)
Requires-Dist: librosa (>=0.9.2,<0.10.0)
Requires-Dist: matplotlib (>=3.6.2,<4.0.0)
Requires-Dist: numpy (>=1.23.5,<2.0.0)
Requires-Dist: scipy (>=1.9.3,<2.0.0)
Requires-Dist: tensorboardX (>=2.5.1,<3.0.0)
Requires-Dist: tensorflow (>=2.11.0,<3.0.0)
Requires-Dist: tensorflow-io-gcs-filesystem (>=0.29.0,<0.30.0) ; python_version >= "3.8" and python_version < "3.11"
Requires-Dist: waveglow (>=22.12.28,<23.0.0)
Project-URL: Documentation, https://test.pypi.org/project/tacotron2
Project-URL: Repository, http://github.com/8tm/tacotron2
